{
  "address": "G9tuE1qzcurDeUQcfgkpeEkLgJC3yGsF7crn53pzD79j",
  "metadata": {
    "name": "prediction_markets",
    "version": "0.1.0",
    "spec": "0.1.0",
    "description": "Solana Saga - Viral Prediction Market Game"
  },
  "instructions": [
    {
      "name": "cancel_market",
      "docs": [
        "Cancel market (only creator, only if no bets placed)"
      ],
      "discriminator": [
        205,
        121,
        84,
        210,
        222,
        71,
        150,
        11
      ],
      "accounts": [
        {
          "name": "market",
          "writable": true
        },
        {
          "name": "creator",
          "signer": true
        }
      ],
      "args": []
    },
    {
      "name": "claim_winnings",
      "docs": [
        "Claim winnings from a resolved market"
      ],
      "discriminator": [
        161,
        215,
        24,
        59,
        14,
        236,
        242,
        221
      ],
      "accounts": [
        {
          "name": "market",
          "pda": {
            "seeds": [
              {
                "kind": "const",
                "value": [
                  109,
                  97,
                  114,
                  107,
                  101,
                  116
                ]
              },
              {
                "kind": "arg",
                "path": "market_id"
              }
            ]
          }
        },
        {
          "name": "bet",
          "writable": true
        },
        {
          "name": "user_stats",
          "writable": true
        },
        {
          "name": "vault",
          "writable": true,
          "pda": {
            "seeds": [
              {
                "kind": "const",
                "value": [
                  118,
                  97,
                  117,
                  108,
                  116
                ]
              },
              {
                "kind": "arg",
                "path": "market_id"
              }
            ]
          }
        },
        {
          "name": "user_token_account",
          "writable": true
        },
        {
          "name": "user",
          "signer": true
        },
        {
          "name": "token_program",
          "address": "TokenkegQfeZyiNwAJbNbGKPFXCWuBvf9Ss623VQ5DA"
        }
      ],
      "args": [
        {
          "name": "_market_id",
          "type": "u64"
        }
      ]
    },
    {
      "name": "create_market",
      "docs": [
        "Create a new prediction market"
      ],
      "discriminator": [
        103,
        226,
        97,
        235,
        200,
        188,
        251,
        254
      ],
      "accounts": [
        {
          "name": "market",
          "writable": true,
          "pda": {
            "seeds": [
              {
                "kind": "const",
                "value": [
                  109,
                  97,
                  114,
                  107,
                  101,
                  116
                ]
              },
              {
                "kind": "arg",
                "path": "market_id"
              }
            ]
          }
        },
        {
          "name": "vault",
          "writable": true,
          "pda": {
            "seeds": [
              {
                "kind": "const",
                "value": [
                  118,
                  97,
                  117,
                  108,
                  116
                ]
              },
              {
                "kind": "arg",
                "path": "market_id"
              }
            ]
          }
        },
        {
          "name": "usdc_mint"
        },
        {
          "name": "creator",
          "writable": true,
          "signer": true
        },
        {
          "name": "token_program",
          "address": "TokenkegQfeZyiNwAJbNbGKPFXCWuBvf9Ss623VQ5DA"
        },
        {
          "name": "system_program",
          "address": "11111111111111111111111111111111"
        }
      ],
      "args": [
        {
          "name": "market_id",
          "type": "u64"
        },
        {
          "name": "question",
          "type": "string"
        },
        {
          "name": "description",
          "type": "string"
        },
        {
          "name": "end_time",
          "type": "i64"
        },
        {
          "name": "category",
          "type": "string"
        }
      ]
    },
    {
      "name": "place_bet",
      "docs": [
        "Place a bet on a market (YES or NO)"
      ],
      "discriminator": [
        222,
        62,
        67,
        220,
        63,
        166,
        126,
        33
      ],
      "accounts": [
        {
          "name": "market",
          "writable": true,
          "pda": {
            "seeds": [
              {
                "kind": "const",
                "value": [
                  109,
                  97,
                  114,
                  107,
                  101,
                  116
                ]
              },
              {
                "kind": "arg",
                "path": "market_id"
              }
            ]
          }
        },
        {
          "name": "bet",
          "writable": true,
          "pda": {
            "seeds": [
              {
                "kind": "const",
                "value": [
                  98,
                  101,
                  116
                ]
              },
              {
                "kind": "account",
                "path": "market"
              },
              {
                "kind": "account",
                "path": "user"
              },
              {
                "kind": "account",
                "path": "market.total_bets_count",
                "account": "Market"
              }
            ]
          }
        },
        {
          "name": "user_stats",
          "writable": true,
          "pda": {
            "seeds": [
              {
                "kind": "const",
                "value": [
                  117,
                  115,
                  101,
                  114,
                  95,
                  115,
                  116,
                  97,
                  116,
                  115
                ]
              },
              {
                "kind": "account",
                "path": "user"
              }
            ]
          }
        },
        {
          "name": "vault",
          "writable": true,
          "pda": {
            "seeds": [
              {
                "kind": "const",
                "value": [
                  118,
                  97,
                  117,
                  108,
                  116
                ]
              },
              {
                "kind": "arg",
                "path": "market_id"
              }
            ]
          }
        },
        {
          "name": "user_token_account",
          "writable": true
        },
        {
          "name": "user",
          "writable": true,
          "signer": true
        },
        {
          "name": "token_program",
          "address": "TokenkegQfeZyiNwAJbNbGKPFXCWuBvf9Ss623VQ5DA"
        },
        {
          "name": "system_program",
          "address": "11111111111111111111111111111111"
        }
      ],
      "args": [
        {
          "name": "_market_id",
          "type": "u64"
        },
        {
          "name": "amount",
          "type": "u64"
        },
        {
          "name": "prediction",
          "type": "bool"
        }
      ]
    },
    {
      "name": "resolve_market",
      "docs": [
        "Resolve market (CREATOR-ONLY - instant resolution)"
      ],
      "discriminator": [
        155,
        23,
        80,
        173,
        46,
        74,
        23,
        239
      ],
      "accounts": [
        {
          "name": "market",
          "writable": true,
          "pda": {
            "seeds": [
              {
                "kind": "const",
                "value": [
                  109,
                  97,
                  114,
                  107,
                  101,
                  116
                ]
              },
              {
                "kind": "arg",
                "path": "market_id"
              }
            ]
          }
        },
        {
          "name": "creator",
          "writable": true,
          "signer": true
        }
      ],
      "args": [
        {
          "name": "_market_id",
          "type": "u64"
        },
        {
          "name": "outcome",
          "type": "bool"
        }
      ]
    }
  ],
  "accounts": [
    {
      "name": "Bet",
      "discriminator": [
        147,
        23,
        35,
        59,
        15,
        75,
        155,
        32
      ]
    },
    {
      "name": "Market",
      "discriminator": [
        219,
        190,
        213,
        55,
        0,
        227,
        198,
        154
      ]
    },
    {
      "name": "UserStats",
      "discriminator": [
        176,
        223,
        136,
        27,
        122,
        79,
        32,
        227
      ]
    }
  ],
  "errors": [
    {
      "code": 6000,
      "name": "QuestionTooLong",
      "msg": "Question too long (max 200 characters)"
    },
    {
      "code": 6001,
      "name": "DescriptionTooLong",
      "msg": "Description too long (max 500 characters)"
    },
    {
      "code": 6002,
      "name": "EndTimeInPast",
      "msg": "End time must be in the future"
    },
    {
      "code": 6003,
      "name": "EndTimeTooFar",
      "msg": "End time too far in the future (max 30 days)"
    },
    {
      "code": 6004,
      "name": "MarketNotActive",
      "msg": "Market is not active"
    },
    {
      "code": 6005,
      "name": "MarketNotEnded",
      "msg": "Market has not ended yet"
    },
    {
      "code": 6006,
      "name": "MarketEnded",
      "msg": "Market already ended"
    },
    {
      "code": 6007,
      "name": "BetTooSmall",
      "msg": "Bet too small (minimum 1 USDC)"
    },
    {
      "code": 6008,
      "name": "BetTooLarge",
      "msg": "Bet too large (maximum 10,000 USDC)"
    },
    {
      "code": 6009,
      "name": "UnauthorizedResolver",
      "msg": "Unauthorized resolver"
    },
    {
      "code": 6010,
      "name": "MarketNotResolved",
      "msg": "Market not resolved yet"
    },
    {
      "code": 6011,
      "name": "AlreadyClaimed",
      "msg": "Already claimed"
    },
    {
      "code": 6012,
      "name": "NotBetOwner",
      "msg": "Not the bet owner"
    },
    {
      "code": 6013,
      "name": "NotCreator",
      "msg": "Not the market creator"
    },
    {
      "code": 6014,
      "name": "HasBets",
      "msg": "Market has bets, cannot cancel"
    },
    {
      "code": 6015,
      "name": "MathOverflow",
      "msg": "Math overflow"
    }
  ],
  "types": [
    {
      "name": "Bet",
      "type": {
        "kind": "struct",
        "fields": [
          {
            "name": "market",
            "type": "pubkey"
          },
          {
            "name": "user",
            "type": "pubkey"
          },
          {
            "name": "amount",
            "type": "u64"
          },
          {
            "name": "tokens_received",
            "type": "u64"
          },
          {
            "name": "prediction",
            "type": "bool"
          },
          {
            "name": "timestamp",
            "type": "i64"
          },
          {
            "name": "claimed",
            "type": "bool"
          },
          {
            "name": "payout",
            "type": "u64"
          }
        ]
      }
    },
    {
      "name": "Market",
      "type": {
        "kind": "struct",
        "fields": [
          {
            "name": "id",
            "type": "u64"
          },
          {
            "name": "question",
            "type": "string"
          },
          {
            "name": "description",
            "type": "string"
          },
          {
            "name": "creator",
            "type": "pubkey"
          },
          {
            "name": "created_at",
            "type": "i64"
          },
          {
            "name": "end_time",
            "type": "i64"
          },
          {
            "name": "resolution_time",
            "type": {
              "option": "i64"
            }
          },
          {
            "name": "outcome",
            "type": {
              "option": "bool"
            }
          },
          {
            "name": "category",
            "type": "string"
          },
          {
            "name": "yes_pool",
            "type": "u64"
          },
          {
            "name": "no_pool",
            "type": "u64"
          },
          {
            "name": "total_yes_bets",
            "type": "u64"
          },
          {
            "name": "total_no_bets",
            "type": "u64"
          },
          {
            "name": "total_volume",
            "type": "u64"
          },
          {
            "name": "total_bets_count",
            "type": "u64"
          },
          {
            "name": "unique_bettors",
            "type": "u64"
          },
          {
            "name": "fee_percentage",
            "type": "u8"
          },
          {
            "name": "status",
            "type": {
              "defined": {
                "name": "MarketStatus"
              }
            }
          },
          {
            "name": "vault",
            "type": "pubkey"
          },
          {
            "name": "vault_bump",
            "type": "u8"
          },
          {
            "name": "resolution_proposer",
            "type": {
              "option": "pubkey"
            }
          },
          {
            "name": "resolution_bond",
            "type": "u64"
          },
          {
            "name": "challenge_deadline",
            "type": {
              "option": "i64"
            }
          },
          {
            "name": "is_finalized",
            "type": "bool"
          },
          {
            "name": "resolver",
            "type": "pubkey"
          }
        ]
      }
    },
    {
      "name": "MarketStatus",
      "type": {
        "kind": "enum",
        "variants": [
          {
            "name": "Active"
          },
          {
            "name": "Resolved"
          },
          {
            "name": "Cancelled"
          }
        ]
      }
    },
    {
      "name": "UserStats",
      "type": {
        "kind": "struct",
        "fields": [
          {
            "name": "user",
            "type": "pubkey"
          },
          {
            "name": "total_bets",
            "type": "u64"
          },
          {
            "name": "total_wagered",
            "type": "u64"
          },
          {
            "name": "total_won",
            "type": "u64"
          },
          {
            "name": "total_lost",
            "type": "u64"
          },
          {
            "name": "win_count",
            "type": "u32"
          },
          {
            "name": "loss_count",
            "type": "u32"
          },
          {
            "name": "current_streak",
            "type": "u32"
          },
          {
            "name": "best_streak",
            "type": "u32"
          },
          {
            "name": "net_profit",
            "type": "i64"
          }
        ]
      }
    }
  ]
}